setup.py
vanHOzone/__init__.py
vanHOzone/vanHOzone.py
vanHOzone.egg-info/PKG-INFO
vanHOzone.egg-info/SOURCES.txt
vanHOzone.egg-info/dependency_links.txt
vanHOzone.egg-info/requires.txt
vanHOzone.egg-info/top_level.txt