Metadata-Version: 1.1
Name: vanHOzone
Version: 1.0.0
Summary: An implementation of the van Heuklon (1979) Ozone model, for estimating atmospheric ozone concentration given a latitude, longitude and datetime.
Home-page: https://pypi.python.org/pypi/vanHOzone
Author: Robin Wilson
Author-email: robin@rtwilson.com
License: MIT
Platform: UNKNOWN
Classifier: Development Status :: 5 - Production/Stable
Classifier: Intended Audience :: Science/Research
Classifier: Topic :: Scientific/Engineering :: Atmospheric Science
Classifier: Topic :: Scientific/Engineering :: Physics
Classifier: Topic :: Software Development :: Libraries :: Python Modules
Classifier: License :: OSI Approved :: MIT License
Classifier: Programming Language :: Python
Classifier: Programming Language :: Python :: 3
Classifier: Programming Language :: Python :: 2
